.DS_Store
equinox/__init__.py
equinox/score.py
equinox_gould29-0.0.5.dist-info/LICENSE
equinox_gould29-0.0.5.dist-info/METADATA
equinox_gould29-0.0.5.dist-info/WHEEL
equinox_gould29-0.0.5.dist-info/top_level.txt
equinox_gould29-0.0.5.dist-info/RECORD
