Metadata-Version: 2.1
Name: equinox-gould29
Version: 0.0.5
Summary: Equinox is a powerful and scalable Python library for calculating inter-annotator agreement scores for a variety of Natural Language Processing and Machine Learning tasks.
Home-page: https://github.com/gouldju1/Equinox
Author: Justin Gould
Author-email: gould29@purdue.edu
License: UNKNOWN
Project-URL: Bug Tracker, https://github.com/gouldju1/Equinox/issues
Platform: UNKNOWN
Classifier: Programming Language :: Python :: 3
Classifier: License :: OSI Approved :: MIT License
Classifier: Operating System :: OS Independent
Requires-Python: >=3.6
